ETLFlow/ETLFlow.py
ETLFlow/__init__.py
brainiac5/__init__.py
brainiac5/brainiac5.py
brainiac5-0.0.22.dist-info/LICENSE
brainiac5-0.0.22.dist-info/METADATA
brainiac5-0.0.22.dist-info/WHEEL
brainiac5-0.0.22.dist-info/top_level.txt
brainiac5-0.0.22.dist-info/RECORD
